MANIFEST.in
README.txt
ez_setup.py
setup.py
thebops/__init__.py
thebops/tools/__init__.py
thebops/tools/modpath.py
thebops/tools/py_env.py
thebops/tools/scanpath.py
thebops_envtools.egg-info/PKG-INFO
thebops_envtools.egg-info/SOURCES.txt
thebops_envtools.egg-info/dependency_links.txt
thebops_envtools.egg-info/entry_points.txt
thebops_envtools.egg-info/namespace_packages.txt
thebops_envtools.egg-info/requires.txt
thebops_envtools.egg-info/top_level.txt