Metadata-Version: 1.0
Name: thebops-envtools
Version: 0.1.2
Summary: Tools for environment variables
Home-page: UNKNOWN
Author: Tobias Herp
Author-email: tobias.herp@gmx.net
License: GPL
Platform: UNKNOWN
